[
    {
        "key": "datr",
        "value": "130MaDba_7S8usBQAvDzYQqt",
        "domain": "facebook.com",
        "path": "/",
        "hostOnly": false,
        "creation": "2025-04-26T06:42:32.256Z",
        "lastAccessed": "2025-04-26T06:42:32.258Z"
    },
    {
        "key": "sb",
        "value": "130MaLi-6LWDrPkPQniN0GPy",
        "domain": "facebook.com",
        "path": "/",
        "hostOnly": false,
        "creation": "2025-04-26T06:42:32.258Z",
        "lastAccessed": "2025-04-26T06:42:32.258Z"
    },
    {
        "key": "dpr",
        "value": "3.2983407974243164",
        "domain": "facebook.com",
        "path": "/",
        "hostOnly": false,
        "creation": "2025-04-26T06:42:32.258Z",
        "lastAccessed": "2025-04-26T06:42:32.258Z"
    },
    {
        "key": "locale",
        "value": "en_US",
        "domain": "facebook.com",
        "path": "/",
        "hostOnly": false,
        "creation": "2025-04-26T06:42:32.258Z",
        "lastAccessed": "2025-04-26T06:42:32.258Z"
    },
    {
        "key": "wl_cbv",
        "value": "v2%3Bclient_version%3A2799%3Btimestamp%3A1745649246",
        "domain": "facebook.com",
        "path": "/",
        "hostOnly": false,
        "creation": "2025-04-26T06:42:32.258Z",
        "lastAccessed": "2025-04-26T06:42:32.258Z"
    },
    {
        "key": "vpd",
        "value": "v1%3B814x407x3",
        "domain": "facebook.com",
        "path": "/",
        "hostOnly": false,
        "creation": "2025-04-26T06:42:32.258Z",
        "lastAccessed": "2025-04-26T06:42:32.258Z"
    },
    {
        "key": "m_pixel_ratio",
        "value": "3",
        "domain": "facebook.com",
        "path": "/",
        "hostOnly": false,
        "creation": "2025-04-26T06:42:32.258Z",
        "lastAccessed": "2025-04-26T06:42:32.258Z"
    },
    {
        "key": "wd",
        "value": "407x814",
        "domain": "facebook.com",
        "path": "/",
        "hostOnly": false,
        "creation": "2025-04-26T06:42:32.258Z",
        "lastAccessed": "2025-04-26T06:42:32.258Z"
    },
    {
        "key": "fr",
        "value": "15qfOX8q2a3zIAvQC.AWeWFaMq8-2Ck2_gqeT1bT61yp3UQg3eT4uRpmeiS0pYh23Zl9c.BoDH5g..AAA.0.0.BoDIBW.AWfP2vQIvqRMUq_LBKOXkZBE5J8",
        "domain": "facebook.com",
        "path": "/",
        "hostOnly": false,
        "creation": "2025-04-26T06:42:32.258Z",
        "lastAccessed": "2025-04-26T06:42:32.258Z"
    }
]
